meu_pacote_aa/__init__.py
meu_pacote_aa/main.py
meu_pacote_aa/modules/__init__.py
meu_pacote_aa/modules/hello.py
meu_pacote_aa-1.10.0.dist-info/LICENCE
meu_pacote_aa-1.10.0.dist-info/METADATA
meu_pacote_aa-1.10.0.dist-info/WHEEL
meu_pacote_aa-1.10.0.dist-info/entry_points.txt
meu_pacote_aa-1.10.0.dist-info/top_level.txt
meu_pacote_aa-1.10.0.dist-info/RECORD
