Metadata-Version: 2.1
Name: meu-pacote-aa
Version: 1.10.0
Summary: Um simples pacote python hmmmm
Author: Rafael Nobre
Author-email: rafaelmedeirosnobre2001@gmail.com
License: MIT
Keywords: meu_pacote_aa
Classifier: Programming Language :: Python :: 3
Classifier: License :: OSI Approved :: MIT License
Classifier: Operating System :: OS Independent
License-File: LICENCE
Requires-Dist: pandas
